ulflib/__init__.py
ulflib/scoping.py
ulflib/sexpr.py
ulflib/ulflib.py
ulflib/util.py
ulflib/tense_tree/__init__.py
ulflib/tense_tree/constants.py
ulflib/tense_tree/preprocess.py
ulflib/tense_tree/temporal_lex.py
ulflib/tense_tree/tense_node.py
ulflib/tense_tree/tense_tree.py
ulflib-0.0.23.dist-info/METADATA
ulflib-0.0.23.dist-info/WHEEL
ulflib-0.0.23.dist-info/licenses/LICENSE
ulflib-0.0.23.dist-info/RECORD
