Metadata-Version: 2.1
Name: ulflib
Version: 0.0.23
Summary: A Python port of the Lisp ulflib package by Gene Kim.
Project-URL: Homepage, https://github.com/bkane2/ulflib-py
Project-URL: Bug Tracker, https://github.com/bkane2/ulflib-py/issues
Author-email: Benjamin Kane <Ben.Kane@me.com>, Gene Kim <genekim@usf.edu>
License-File: LICENSE
Classifier: License :: OSI Approved :: MIT License
Classifier: Operating System :: OS Independent
Classifier: Programming Language :: Python :: 3
Requires-Python: >=3.7
Requires-Dist: memoization>=0.4.0
Requires-Dist: transduction>=0.1.3
